myvault/__init__.py
myvault/__main__.py
myvault/cli.py
myvault/sql/create_table.sql
myvault/sql/delete_secret.sql
myvault/sql/insert_secret.sql
myvault/sql/select_all.sql
myvault/sql/select_folder_name.sql
myvault/sql/select_secret.sql
myvault/sql/update_secret.sql
myvault/statics/__init__.py
myvault/statics/exit_code.py
myvault/statics/formatted_enum.py
myvault/statics/message.py
myvault/statics/prompt.py
myvault/statics/query.py
myvault/utils/__init__.py
myvault/utils/database.py
myvault/utils/encryption.py
myvault/utils/vault.py
myvault-0.0.2.dist-info/entry_points.txt
myvault-0.0.2.dist-info/LICENSE
myvault-0.0.2.dist-info/WHEEL
myvault-0.0.2.dist-info/METADATA
myvault-0.0.2.dist-info/RECORD
