Metadata-Version: 2.1
Name: myvault
Version: 0.0.2
Summary: A simple, offline vault to store secrets e.g. your password.
Home-page: https://github.com/srtamrakar/vault
License: MIT
Author: Samyak Tamrakar
Requires-Python: >=3.7,<4.0
Classifier: Development Status :: 4 - Beta
Classifier: License :: OSI Approved :: MIT License
Classifier: Operating System :: OS Independent
Classifier: Programming Language :: Python :: 3
Classifier: Programming Language :: Python :: 3.7
Classifier: Programming Language :: Python :: 3.8
Classifier: Programming Language :: Python :: 3.9
Classifier: Topic :: Security :: Cryptography
Requires-Dist: click (>=8.0,<9.0)
Requires-Dist: colorama (>=0.4.4,<0.5.0)
Requires-Dist: pycryptodome (>=3.10,<4.0)
Requires-Dist: pyperclip (>=1.8,<2.0)
